<?xml version="1.0"?>
<opencv_storage>
<stage2>
  <maxWeakCount>2</maxWeakCount>
  <stageThreshold>-1.7621389031410217e-01</stageThreshold>
  <weakClassifiers>
    <_>
      <internalNodes>
        0 -1 4220254 3.2940236851572990e-03</internalNodes>
      <leafValues>
        -9.4999998807907104e-01 8.9999997615814209e-01</leafValues></_>
    <_>
      <internalNodes>
        0 -1 3706148 -2.0113722421228886e-03</internalNodes>
      <leafValues>
        7.7378612756729126e-01 -1.</leafValues></_></weakClassifiers></stage2>
</opencv_storage>
