<?xml version="1.0"?>
<opencv_storage>
<stage0>
  <maxWeakCount>2</maxWeakCount>
  <stageThreshold>-9.4106018543243408e-02</stageThreshold>
  <weakClassifiers>
    <_>
      <internalNodes>
        0 -1 1073516 -1.4213676564395428e-02</internalNodes>
      <leafValues>
        9.6039605140686035e-01 -9.8994976282119751e-01</leafValues></_>
    <_>
      <internalNodes>
        0 -1 779034 7.1325018070638180e-03</internalNodes>
      <leafValues>
        -1. 8.9584374427795410e-01</leafValues></_></weakClassifiers></stage0>
</opencv_storage>
