<?xml version="1.0"?>
<opencv_storage>
<stage3>
  <maxWeakCount>2</maxWeakCount>
  <stageThreshold>-1.4094167947769165e-01</stageThreshold>
  <weakClassifiers>
    <_>
      <internalNodes>
        0 -1 1750375 5.6855636648833752e-04</internalNodes>
      <leafValues>
        -9.3939393758773804e-01 8.4313726425170898e-01</leafValues></_>
    <_>
      <internalNodes>
        0 -1 4782259 9.7526048193685710e-05</internalNodes>
      <leafValues>
        -1. 7.9845225811004639e-01</leafValues></_></weakClassifiers></stage3>
</opencv_storage>
